MANIFEST.in
setup.cfg
setup.py
garlicsim/__init__.py
garlicsim/lgpl2.1_license.txt
garlicsim/asynchronous_crunching/__init__.py
garlicsim/asynchronous_crunching/base_cruncher.py
garlicsim/asynchronous_crunching/crunching_manager.py
garlicsim/asynchronous_crunching/crunching_profile.py
garlicsim/asynchronous_crunching/history_browser.py
garlicsim/asynchronous_crunching/job.py
garlicsim/asynchronous_crunching/obsolete_cruncher_error.py
garlicsim/asynchronous_crunching/project.py
garlicsim/asynchronous_crunching/crunchers/__init__.py
garlicsim/asynchronous_crunching/crunchers/thread_cruncher.py
garlicsim/asynchronous_crunching/crunchers/pi_cloud_cruncher/__init__.py
garlicsim/asynchronous_crunching/crunchers/pi_cloud_cruncher/pi_cloud_cruncher.py
garlicsim/asynchronous_crunching/crunchers/process_cruncher/__init__.py
garlicsim/asynchronous_crunching/crunchers/process_cruncher/process.py
garlicsim/asynchronous_crunching/crunchers/process_cruncher/process_cruncher.py
garlicsim/asynchronous_crunching/misc/__init__.py
garlicsim/asynchronous_crunching/misc/end_marker.py
garlicsim/bootstrap/__init__.py
garlicsim/bootstrap/bootstrap.py
garlicsim/data_structures/__init__.py
garlicsim/data_structures/block.py
garlicsim/data_structures/end.py
garlicsim/data_structures/node.py
garlicsim/data_structures/node_range.py
garlicsim/data_structures/node_selection.py
garlicsim/data_structures/path.py
garlicsim/data_structures/state.py
garlicsim/data_structures/tree.py
garlicsim/data_structures/tree_member.py
garlicsim/general_misc/__init__.py
garlicsim/general_misc/abc_tools.py
garlicsim/general_misc/arguments_profile.py
garlicsim/general_misc/change_tracker.py
garlicsim/general_misc/cmp_tools.py
garlicsim/general_misc/context_manager.py
garlicsim/general_misc/copy_mode.py
garlicsim/general_misc/copy_tools.py
garlicsim/general_misc/cute_iter_tools.py
garlicsim/general_misc/cute_testing.py
garlicsim/general_misc/decorator_tools.py
garlicsim/general_misc/dict_tools.py
garlicsim_py3.egg-info/PKG-INFO
garlicsim_py3.egg-info/SOURCES.txt
garlicsim_py3.egg-info/dependency_links.txt
garlicsim_py3.egg-info/not-zip-safe
garlicsim_py3.egg-info/requires.txt
garlicsim_py3.egg-info/top_level.txt
